{
  "type": "object",
  "required": [
    "valueType",
    "favorite",
    "version",
    "externalAccess"
  ],
  "properties": {
    "access": {
      "$ref": "Access.json"
    },
    "attributeValues": {
      "type": "array",
      "items": {
        "$ref": "AttributeValue.json"
      }
    },
    "code": {
      "type": "string"
    },
    "created": {
      "type": "string",
      "format": "date-time"
    },
    "createdBy": {
      "$ref": "Ref-User.json"
    },
    "description": {
      "type": "string"
    },
    "displayName": {
      "type": "string"
    },
    "externalAccess": {
      "type": "boolean"
    },
    "favorite": {
      "type": "boolean"
    },
    "favorites": {
      "type": "array",
      "items": {
        "type": "string"
      }
    },
    "href": {
      "type": "string"
    },
    "id": {
      "type": "string"
    },
    "lastUpdated": {
      "type": "string",
      "format": "date-time"
    },
    "lastUpdatedBy": {
      "$ref": "Ref-User.json"
    },
    "name": {
      "type": "string"
    },
    "options": {
      "type": "array",
      "items": {
        "$ref": "Ref-Option.json"
      }
    },
    "publicAccess": {
      "type": "string"
    },
    "sharing": {
      "$ref": "Sharing.json"
    },
    "translations": {
      "type": "array",
      "items": {
        "$ref": "Translation.json"
      }
    },
    "user": {
      "$ref": "Ref-User.json"
    },
    "userAccesses": {
      "type": "array",
      "items": {
        "$ref": "UserAccess.json"
      }
    },
    "userGroupAccesses": {
      "type": "array",
      "items": {
        "$ref": "UserGroupAccess.json"
      }
    },
    "valueType": {
      "type": "string",
      "enum": [
        "TEXT",
        "LONG_TEXT",
        "MULTI_TEXT",
        "LETTER",
        "PHONE_NUMBER",
        "EMAIL",
        "BOOLEAN",
        "TRUE_ONLY",
        "DATE",
        "DATETIME",
        "TIME",
        "NUMBER",
        "UNIT_INTERVAL",
        "PERCENTAGE",
        "INTEGER",
        "INTEGER_POSITIVE",
        "INTEGER_NEGATIVE",
        "INTEGER_ZERO_OR_POSITIVE",
        "TRACKER_ASSOCIATE",
        "USERNAME",
        "COORDINATE",
        "ORGANISATION_UNIT",
        "REFERENCE",
        "AGE",
        "URL",
        "FILE_RESOURCE",
        "IMAGE",
        "GEOJSON"
      ]
    },
    "version": {
      "type": "integer",
      "format": "int32"
    }
  }
}
